contrabass/__init__.py
contrabass/cli/__init__.py
contrabass/cli/commands.py
contrabass/cli/main.py
contrabass/cli/utils.py
contrabass/core/CobraMetabolicModel.py
contrabass/core/Facade.py
contrabass/core/FacadeThread.py
contrabass/core/FacadeUtils.py
contrabass/core/Spreadsheet.py
contrabass/core/State.py
contrabass/core/__init__.py
contrabass/core/report_utils.py
contrabass/core/util.py
contrabass/core/templates/__init__.py
contrabass/core/templates/html/__init__.py
contrabass/core/templates/html/template.html
contrabass/core/templates/html/template_cp.html
contrabass/core/utils/CriticalCPConfig.py
contrabass/core/utils/CustomLogger.py
contrabass/core/utils/GrowthDependentCPConfig.py
contrabass/core/utils/__init__.py
contrabass-0.2.1.dist-info/LICENSE
contrabass-0.2.1.dist-info/METADATA
contrabass-0.2.1.dist-info/WHEEL
contrabass-0.2.1.dist-info/entry_points.txt
contrabass-0.2.1.dist-info/top_level.txt
contrabass-0.2.1.dist-info/RECORD
