Metadata-Version: 2.1
Name: contrabass
Version: 0.2.1
Summary: Constraint-based model vulnerabilities analysis
Home-page: https://github.com/openCONTRABASS/CONTRABASS
Author: Alex Oarga
Author-email: 718123@unizar.es
License: GNU General Public License v3 or later (GPLv3+)
Platform: UNKNOWN
Classifier: Programming Language :: Python :: 3
Classifier: License :: OSI Approved :: GNU General Public License v3 or later (GPLv3+)
Classifier: Operating System :: OS Independent
License-File: LICENSE
Requires-Dist: cobra (==0.16.0)
Requires-Dist: click
Requires-Dist: depinfo
Requires-Dist: python-dotenv
Requires-Dist: future
Requires-Dist: Jinja2
Requires-Dist: mpmath
Requires-Dist: numpy (>=1.16.5)
Requires-Dist: optlang (>=1.4.2)
Requires-Dist: pandas (>=0.17.0)
Requires-Dist: python-dateutil
Requires-Dist: python-libsbml
Requires-Dist: python-libsbml-experimental (==5.18.0)
Requires-Dist: pytz
Requires-Dist: ruamel.yaml (>=0.15)
Requires-Dist: setuptools
Requires-Dist: six
Requires-Dist: swiglpk
Requires-Dist: sympy
Requires-Dist: tabulate
Requires-Dist: xlwt (==1.3.0)
